<?xml version="1.0" encoding="utf-8"?>
<openerp>
    <data>
        <report
            id="anl_sales_quotation_report_id"
            model="sale.order"
            string="Anl Sales Quotation"
            report_type="qweb-pdf"
            name="report_sales.report_anl_sales_quotation"
            file="report_sales.report_anl_sales_quotation"
        />

        <report
            id="anl_sales_agreement_report_id"
            model="sale.order"
            string="Anl Sales Agreement"
            report_type="qweb-pdf"
            name="report_sales.report_anl_sales_agreement"
            file="report_sales.report_anl_sales_agreement"
        />

        <report
            id="anl_sales_invoice_report_id"
            model="account.invoice"
            string="Anl Sales Invoice"
            report_type="qweb-pdf"
            name="report_sales.report_anl_invoice"
            file="report_sales.report_anl_invoice"
        />

        <report
            id="anl_sales_delivery_report_id"
            model="stock.picking"
            string="Anl Delivery Order"
            report_type="qweb-pdf"
            name="report_sales.report_anl_delivery"
            file="report_sales.report_anl_delivery"
        />
        
        <record id="paperformat_lowmargin" model="report.paperformat">
        	<field name="name">Custom A4 Margin</field>
   		    <field name="default" eval="True" />
    		<field name="format">A4</field>
    		<field name="page_height">0</field>
    		<field name="page_width">0</field>
    		<field name="orientation">Portrait</field>
    		<field name="margin_top">30</field> <!-- Controls the header height -->
    		<field name="margin_bottom">4</field> <!-- Controls the footer height -->
    		<field name="margin_left">4</field>
    		<field name="margin_right">4</field>
    		<field name="header_line" eval="False" />
    		<field name="header_spacing">25</field> <!-- Controls the body starting from the top page -->
    		<field name="dpi">90</field>
		</record>
		
		<record id="report_sales.anl_sales_agreement_report_id" model="ir.actions.report.xml">
    		<field name="paperformat_id" ref="report_sales.paperformat_lowmargin" />
		</record>


    </data>
</openerp>